kobo/__init__.py
kobo/cli.py
kobo/conf.py
kobo/decorators.py
kobo/exceptions.py
kobo/hardlink.py
kobo/http.py
kobo/log.py
kobo/notification.py
kobo/pkgset.py
kobo/plugins.py
kobo/process.py
kobo/rpmlib.py
kobo/shortcuts.py
kobo/tback.py
kobo/threads.py
kobo/types.py
kobo/xmlrpc.py
kobo/admin/__init__.py
kobo/admin/kobo-admin
kobo/admin/commands/__init__.py
kobo/admin/commands/cmd_start_cli.py
kobo/admin/commands/cmd_start_cli_command.py
kobo/admin/commands/cmd_start_client.py
kobo/admin/commands/cmd_start_client_command.py
kobo/admin/commands/cmd_start_hub.py
kobo/admin/commands/cmd_start_worker.py
kobo/admin/commands/cmd_start_worker_task.py
kobo/admin/templates/cli@cmd___project_name__.py.template
kobo/admin/templates/client@cmd___project_name__.py.template
kobo/admin/templates/task___project_name__.py.template
kobo/admin/templates/cli/__init__.py.template
kobo/admin/templates/cli/__project_name__
kobo/admin/templates/cli/commands/__init__.py.template
kobo/admin/templates/client/__init__.py.template
kobo/admin/templates/client/__project_name__
kobo/admin/templates/client/__project_name__.conf
kobo/admin/templates/client/commands/__init__.py.template
kobo/admin/templates/hub/__init__.py.template
kobo/admin/templates/hub/__project_name__-httpd.conf
kobo/admin/templates/hub/__project_name__.wsgi
kobo/admin/templates/hub/manage.py.template
kobo/admin/templates/hub/menu.py.template
kobo/admin/templates/hub/settings.py.template
kobo/admin/templates/hub/settings_local.py.template
kobo/admin/templates/hub/urls.py.template
kobo/admin/templates/hub/templates/base.html
kobo/admin/templates/hub/templates/index.html
kobo/admin/templates/hub/xmlrpc/__init__.py.template
kobo/admin/templates/hub/xmlrpc/urls.py.template
kobo/admin/templates/worker/__init__.py.template
kobo/admin/templates/worker/__project_name__
kobo/admin/templates/worker/__project_name__.conf
kobo/admin/templates/worker/tasks/__init__.py.template
kobo/client/__init__.py
kobo/client/constants.py
kobo-0.41.0.dist-info/licenses/AUTHORS
kobo-0.41.0.dist-info/licenses/COPYING
kobo-0.41.0.dist-info/licenses/LICENSE
kobo-0.41.0.dist-info/METADATA
kobo-0.41.0.dist-info/WHEEL
kobo-0.41.0.dist-info/top_level.txt
kobo-0.41.0.dist-info/RECORD
