Metadata-Version: 2.4
Name: kobo
Version: 0.41.0
Summary: A pile of python modules used by Red Hat release engineering to build their tools
Home-page: https://github.com/release-engineering/kobo/
Author: Red Hat, Inc.
Author-email: dmach@redhat.com
License: LGPLv2.1
Requires-Python: >=3.6
License-File: LICENSE
License-File: COPYING
License-File: AUTHORS
Requires-Dist: six
Dynamic: author
Dynamic: author-email
Dynamic: home-page
Dynamic: license
Dynamic: license-file
Dynamic: requires-dist
Dynamic: requires-python
Dynamic: summary
